cli/COPYRIGHT.txt
cli/LICENSE.md
cli/__init__.py
cli/args.py
cli/config.py
cli/docker.py
cli/main.py
cli/utils.py
flexbench/COPYRIGHT.txt
flexbench/Dockerfile
flexbench/LICENSE.md
flexbench/README.md
flexbench/__init__.py
flexbench/__main__.py
flexbench/accuracy_check.py
flexbench/args.py
flexbench/config.py
flexbench/main.py
flexbench/mlperf.conf
flexbench/pyproject.toml
flexbench/user.conf
flexbench/utils.py
flexbench/uv.lock
flexbench/dataset/__init__.py
flexbench/dataset/base.py
flexbench/dataset/text.py
flexbench/runners/__init__.py
flexbench/runners/base.py
flexbench/runners/factory.py
flexbench/runners/loadgen/backend.py
flexbench/runners/loadgen/runner.py
flexbench/runners/vllm/backend.py
flexbench/runners/vllm/runner.py
flexbench-0.2.0.dist-info/licenses/LICENSE.md
flexboard/COPYRIGHT.txt
flexboard/Dockerfile
flexboard/LICENSE.md
flexboard/README.md
flexboard/accelerator_prices.json
flexboard/app.py
flexboard/plots.py
flexboard/processor.py
flexboard/pyproject.toml
flexboard/uv.lock
flexboard/pages/1_home.py
flexboard/pages/2_performance.py
flexboard/pages/3_cost.py
flexbench-0.2.0.dist-info/METADATA
flexbench-0.2.0.dist-info/WHEEL
flexbench-0.2.0.dist-info/entry_points.txt
flexbench-0.2.0.dist-info/top_level.txt
flexbench-0.2.0.dist-info/RECORD
