Metadata-Version: 2.4
Name: flexbench
Version: 0.2.0
Summary: FlexBench CLI - Docker orchestration for FlexAI Universal Benchmarking
Author: Daniel Altunay, Grigori Fursin
License: Apache-2.0
Classifier: Programming Language :: Python :: 3.12
Requires-Python: >=3.12
License-File: LICENSE.md
Requires-Dist: aiohttp>=3.12.13
Requires-Dist: pyyaml>=6.0.2
Requires-Dist: typer>=0.16.0
Dynamic: license-file
